Workbook

Sheet Read Me
A1: Suffolk County Appliance Repair - SEO Silo Plan
A2: 98 pages: 5 main, 8 core services, 6 specialty services, 5 town hubs, 4 supporting pages, and 70 service-by-town pages (14 services x 5 towns).
A4: How to use
A5: 1. 'SEO Silo' is the master sheet: URL slug, meta title, meta description, SEO content, internal and external links for every page.
A6: 2. Meta lengths, word counts, link counts and the word check are live formulas. Edit the blue Word Target cells or the text and they update.
A7: 3. 'Link Map' lists every internal and external link as source -> anchor -> target, ready for your developer or WordPress builder.
A8: 4. 'Blog Topics' has 14 supporting articles that link into the silos.
A10: Silo structure
A11: Home -> All Services -> Service page (e.g. /refrigerator-repair/) -> Service + town page (e.g. /refrigerator-repair/huntington-ny/).
A12: Town hubs (/appliance-repair-huntington-ny/) link down to all 14 service pages for that town. Service-town pages link back up to their service and town hub, sideways to the nearest town, and to 2 related services in the same town.
A14: Placeholders to replace before publishing (in square brackets in the content)
A15: [BUSINESS NAME], [PHONE], [INSERT WARRANTY], [INSERT DIAGNOSTIC FEE POLICY], [INSERT SAME-DAY / NEXT-DAY POLICY], [INSERT LICENSING / INSURANCE], plus review, team and address placeholders. Only state licenses, warranties, response times and reviews that are real.
... A24: - Meta titles are capped at 60 characters and descriptions at 155. Titles contain [BUSINESS NAME] on a few pages; replace it and re-check the length.

Sheet Summary
A1: Page counts and content totals
A3: Page Type | B3: Pages | C3: Total Words | D3: Avg Words | E3: Pages Passing Word Check
A4: Main | B4: =COUNTIF('SEO Silo'!$B$2:$B$99,A4) -> 5 | C4: =SUMIF('SEO Silo'!$B$2:$B$99,A4,'SEO Silo'!$M$2:$M$99) -> 3702 | D4: =IF(B4=0,0,ROUND(C4/B4,0)) -> 740 | E4: =COUNTIFS('SEO Silo'!$B$2:$B$99,A4,'SEO Silo'!$N$2:$N$99,"OK") -> 5
A5: Core Service | B5: =COUNTIF('SEO Silo'!$B$2:$B$99,A5) -> 8 | C5: =SUMIF('SEO Silo'!$B$2:$B$99,A5,'SEO Silo'!$M$2:$M$99) -> 7937 | D5: =IF(B5=0,0,ROUND(C5/B5,0)) -> 992 | E5: =COUNTIFS('SEO Silo'!$B$2:$B$99,A5,'SEO Silo'!$N$2:$N$99,"OK") -> 8
A6: Specialty Service | B6: =COUNTIF('SEO Silo'!$B$2:$B$99,A6) -> 6 | C6: =SUMIF('SEO Silo'!$B$2:$B$99,A6,'SEO Silo'!$M$2:$M$99) -> 5411 | D6: =IF(B6=0,0,ROUND(C6/B6,0)) -> 902 | E6: =COUNTIFS('SEO Silo'!$B$2:$B$99,A6,'SEO Silo'!$N$2:$N$99,"OK") -> 6
A7: Town Hub | B7: =COUNTIF('SEO Silo'!$B$2:$B$99,A7) -> 5 | C7: =SUMIF('SEO Silo'!$B$2:$B$99,A7,'SEO Silo'!$M$2:$M$99) -> 4242 | D7: =IF(B7=0,0,ROUND(C7/B7,0)) -> 848 | E7: =COUNTIFS('SEO Silo'!$B$2:$B$99,A7,'SEO Silo'!$N$2:$N$99,"OK") -> 5
A8: Supporting | B8: =COUNTIF('SEO Silo'!$B$2:$B$99,A8) -> 4 | C8: =SUMIF('SEO Silo'!$B$2:$B$99,A8,'SEO Silo'!$M$2:$M$99) -> 1557 | D8: =IF(B8=0,0,ROUND(C8/B8,0)) -> 389 | E8: =COUNTIFS('SEO Silo'!$B$2:$B$99,A8,'SEO Silo'!$N$2:$N$99,"OK") -> 4
A9: Service + Location | B9: =COUNTIF('SEO Silo'!$B$2:$B$99,A9) -> 70 | C9: =SUMIF('SEO Silo'!$B$2:$B$99,A9,'SEO Silo'!$M$2:$M$99) -> 57262 | D9: =IF(B9=0,0,ROUND(C9/B9,0)) -> 818 | E9: =COUNTIFS('SEO Silo'!$B$2:$B$99,A9,'SEO Silo'!$N$2:$N$99,"OK") -> 70
A10: Total | B10: =SUM(B4:B9) -> 98 | C10: =SUM(C4:C9) -> 80111 | D10: =IF(B10=0,0,ROUND(C10/B10,0)) -> 817 | E10: =SUM(E4:E9) -> 98
A12: Total internal links | B12: =COUNTIF('Link Map'!$D$2:$D$987,"Internal") -> 805
A13: Total external links | B13: =COUNTIF('Link Map'!$D$2:$D$987,"External") -> 181
A14: Meta titles over 60 chars | B14: =COUNTIF('SEO Silo'!$H$2:$H$99,">60") -> 0
A15: Meta descriptions over 155 chars | B15: =COUNTIF('SEO Silo'!$J$2:$J$99,">155") -> 0

Sheet SEO Silo
A1: # | B1: Page Type | C1: Silo / Parent | D1: Page Title (H1) | E1: URL Slug | F1: Target Keyword | G1: Meta Title | H1: Title Chars | I1: Meta Description | J1: Desc Chars | K1: Words Min | L1: Words Max | M1: Actual Words | N1: Word Check | O1: SEO Content | P1: Internal Links (anchor -> URL) | Q1: Internal Link Count | R1: External Links (anchor -> URL) | S1: Schema Suggestion | T1: Status
A2: 1 | B2: Main | C2: Home | D2: Home | E2: / | F2: Appliance Repair Suffolk County NY | G2: Appliance Repair Suffolk County, NY | [BUSINESS NAME] | H2: =LEN(G2) -> 53 | I2: Fast, reliable appliance repair across Suffolk County, NY. Refrigerators, washers, dryers, ovens and more. Upfront quotes. Call [PHONE]. | J2: =LEN(I2) -> 136 | K2: 1500 | L2: 2000 | M2: 1565 | N2: =IF(AND(M2>=K2,M2<=L2),"OK","Check") -> OK | O2: H1: Appliance Repair in Suffolk County, NY When your refrigerator warms up, your washer floods the floor or your oven goes cold, you need a repair technician you can trust. [BUSINESS NAME] provides professional appliance repair across Suffolk County, Long Island, for homeowners, renters, landlords and local businesses. We diagnose the fault, explain it in plain language and give you a firm price before starting work. Call [PHONE] or book online to schedule your appointment. We service refrigerators, freezers, washers, dryers, dishwashers, ovens, stoves, cooktops, microwaves, ice makers, wine coolers, garbage disposals and commercial and luxury appliances. H2: Our Appliance Repair Services H3: Refrigerator Repair A refrigerator that stops cooling puts hundreds of dollars of food at risk within hours, so fast and accurate diagnosis matters. We repair top-freezer, bottom-freezer, side-by-side, French-door and counter-depth models. H3: Freezer Repair Whether it is a chest freezer in the garage or an upright in the basement, a failing freezer can ruin weeks of groceries before you notice. We repair upright, chest, built-in and combination freezers. H3: Washing Machine Repair When your washing machine stops draining, spinning or filling, laundry day grinds to a halt. We repair top-load, front-load, high-efficiency and stackable washers. H3: Dryer Repair A dryer that takes two cycles to dry a load is wasting energy and can be a fire hazard. We repair gas and electric dryers, including stackable and ventless models. H3: Dishwasher Repair A dishwasher that leaves dishes dirty, leaks or never drains turns a daily convenience into a daily headache. We repair built-in, drawer and portable dishwashers. H3: Oven Repair When your oven won't heat or bakes unevenly, dinner plans fall apart. We repair single and double wall ovens, electric and gas ovens and convection models. H3: Stove & Range Repair Your range is the workhorse of the kitchen, and a single failed burner or oven element can disrupt daily meals. We repair gas, electric, dual-fuel and induction stoves and ranges. H3: Cooktop Repair Built-in cooktops are the centerpiece of many Suffolk County kitchens, and they need careful, brand-aware service. We repair gas, electric, radiant and induction cooktops. H3: Microwave Repair Microwaves are used several times a day, so a unit that sparks, stops heating or won't start disrupts the kitchen quickly. We service countertop, over-the-range and built-in microwaves. H3: Ice Maker Repair A refrigerator ice maker or stand-alone ice machine that stops producing ice is a frequent complaint, especially in summer. We repair built-in, under-counter and refrigerator-mounted ice makers. H3: Wine Cooler Repair Wine needs steady temperature and humidity, so even small cooling faults can harm a collection. We repair built-in, freestanding, dual-zone and under-counter wine coolers. H3: Garbage Disposal Repair A jammed or leaking garbage disposal can back up your kitchen sink and disrupt dishwasher drainage. We repair and replace continuous-feed and batch-feed disposals. H3: Commercial Appliance Repair For restaurants, delis, cafes and shops, downtime costs money every hour. We repair commercial refrigeration, ranges, ovens, fryers, ice machines and other kitchen equipment. H3: Luxury Appliance Repair Premium appliances demand technicians who understand their design and parts. We repair high-end refrigeration, ranges, wall ovens, cooktops and wine storage. H2: Why Suffolk County Homeowners Call Us Appliances are a big part of daily life, so repair should be simple, honest and fast. Here is what you can expect from our team: - Upfront, written pricing before any repair begins. - Experienced technicians for all major brands. - Common parts carried so many repairs are finished in one visit. - Clear explanations and honest repair-or-replace advice. - Clean, respectful service in your home. - Warranty on parts and labor: [INSERT WARRANTY]. H2: How It Works 1. Contact us by phone or online and describe the problem. 2. We schedule the earliest suitable appointment window. 3. Your technician diagnoses the fault and provides a firm quote. 4. We repair and test your appliance, then provide an invoice and warranty details. H2: Where We Work We serve homes and businesses throughout Suffolk County. Our main service areas include: H3: Appliance Repair in Huntington, NY Huntington blends a walkable historic village with established North Shore neighborhoods, many of them with older kitchens, finished basements and a mix of classic and high-end appliances. We cover Huntington Village, Huntington Station, Greenlawn, Halesite, and Cold Spring Harbor and nearby neighborhoods. H3: Appliance Repair in Smithtown, NY Smithtown is largely suburban, with family-sized homes, busy kitchens and households that run several appliances every single day. We cover Smithtown, Kings Park, St. James, Nesconset, and Hauppauge and nearby neighborhoods. H3: Appliance Repair in Islip, NY Islip stretches across the South Shore, from waterfront communities near the Great South Bay to inland neighborhoods, with a wide mix of single-family homes, condos and rentals. We cover Islip, East Islip, Islip Terrace, Bay Shore, and Brentwood and nearby neighborhoods. H3: Appliance Repair in Babylon, NY The Town of Babylon covers busy South Shore villages and hamlets with a large share of well-kept single-family homes, plus apartments and rental units. We cover Babylon Village, Lindenhurst, Copiague, West Babylon, and North Babylon and nearby neighborhoods. H3: Appliance Repair in Patchogue, NY Patchogue is a lively waterfront village with a walkable downtown, surrounded by neighborhoods of single-family homes, condos and apartments. We cover Patchogue Village, East Patchogue, North Patchogue, Blue Point, and Bellport and nearby neighborhoods. H2: Brands We Repair Our technicians service most major brands, including Whirlpool, GE, Samsung, LG, Frigidaire, Maytag, KitchenAid, Bosch, Electrolux, Sub-Zero, Wolf, Viking, Thermador and Miele. If your brand is not listed, contact us and we will let you know whether we can help. H2: Signs It Is Time to Call a Technician - Your refrigerator or freezer is not holding temperature. - Your washer is leaking, not draining or making grinding noises. - Your dryer takes multiple cycles to dry clothes. - Your dishwasher leaves dishes dirty or standing water. - Your oven, range or cooktop will not heat or ignite. - Your ice maker has stopped producing ice. Addressing small problems early often prevents bigger, more expensive failures. H2: Residential and Commercial Customers We repair household appliances for homeowners, tenants and landlords, and we also service commercial refrigeration, ice machines and cooking equipment for restaurants, cafes and shops that cannot afford extended downtime. Property managers can contact us about repairs across multiple units. H2: Frequently Asked Questions Q: What areas do you serve? A: We serve Suffolk County, with dedicated pages for Huntington, Smithtown, Islip, Babylon and Patchogue. Contact us to confirm your address. Q: How quickly can you schedule a repair? A: Availability varies. [INSERT SAME-DAY / NEXT-DAY POLICY]. We offer the earliest appointment we have. Q: Do you give a price before you start? A: Yes. We diagnose first and give you a written price, and no work begins until you agree. Q: Is it better to repair or replace an old appliance? A: It depends on age, repair cost and reliability. We give an honest recommendation, even if that means replacement. Q: Do you offer a warranty? A: Yes. [INSERT WARRANTY TERMS]. H2: Book Your Appliance Repair Today Call [PHONE] or request service online. Whatever the problem, we will help get your appliance running again. H2: Appliance Care Tips From Our Technicians Most breakdowns can be delayed with simple habits. Vacuum refrigerator coils twice a year, clean dryer lint screens after every load and have the vent line cleaned annually. Clean dishwasher filters monthly, wipe oven and range spills promptly and leave washer doors ajar after use. If you notice odd noises, smells or leaks, call early. Small repairs cost much less than emergency replacements. H2: Repair or Replace? A widely used rule of thumb is that if a repair costs more than about half the price of a comparable new appliance and the unit is past two-thirds of its expected lifespan, replacement deserves serious thought. Newer models can also be more energy-efficient. We always give you the numbers and let you decide, and we never pressure you toward a repair that is not worthwhile. H2: Safety Comes First Gas smells, burning odors, sparking, water near electrical components and overheating dryers are all reasons to stop using an appliance immediately. If you smell gas, leave the home and call your gas utility or emergency services. Our technicians are trained to work safely around gas and electrical systems and will explain any safety concerns we find. H2: Preparing for Your Appointment Have the brand, model and serial number ready, clear the area around the appliance and write down any error codes. Let us know about parking or building access. These small steps help the technician diagnose and repair faster. H2: Preventive Maintenance and Installation Beyond repairs, we can help keep your appliances running longer with preventive maintenance such as coil cleaning, vent cleaning, gasket checks and performance testing. We can also advise on installation of new appliances and haul-away options: [INSERT INSTALLATION / MAINTENANCE SERVICES YOU OFFER]. Regular maintenance catches worn parts before they fail, which reduces energy use and the risk of a breakdown at the worst possible moment, such as the week of a holiday dinner or in the middle of a summer heat wave. H2: What Our Customers Say [INSERT REAL CUSTOMER REVIEWS WITH PERMISSION AND ACCURATE ATTRIBUTION. Do not publish invented testimonials.] We encourage honest feedback and respond to every review. See our reviews page for more. H2: Helpful Guides From Our Technicians Before you call, our troubleshooting articles can help you decide whether a problem is a quick fix or needs a professional. Learn why a refrigerator is not cooling, why a dryer takes too long to dry and what to check when a washer will not drain. Visit our blog for more. | P2: Refrigerator Repair -> /refrigerator-repair/ Freezer Repair -> /freezer-repair/ Washing Machine Repair -> /washer-repair/ Dryer Repair -> /dryer-repair/ Dishwasher Repair -> /dishwasher-repair/ Oven Repair -> /oven-repair/ Stove & Range Repair -> /stove-range-repair/ Cooktop Repair -> /cooktop-repair/ Appliance Repair Huntington -> /appliance-repair-huntington-ny/ Appliance Repair Smithtown -> /appliance-repair-smithtown-ny/ Appliance Repair Islip -> /appliance-repair-islip-ny/ Appliance Repair Babylon -> /appliance-repair-babylon-ny/ Appliance Repair Patchogue -> /appliance-repair-patchogue-ny/ All Appliance Repair Services -> /appliance-repair-services/ Brands We Service -> /appliance-brands/ Reviews -> /reviews/ Contact Us -> /contact/ | Q2: =LEN(P2)-LEN(SUBSTITUTE(P2,CHAR(10),""))+1 -> 17 | R2: ENERGY STAR certified products -> https://www.energystar.gov/products | S2: LocalBusiness / HomeAndConstructionBusiness | T2: To do
A3: 2 | B3: Main | C3: Services Hub | D3: All Services | E3: /appliance-repair-services/ | F3: Appliance Repair Services Suffolk County NY | G3: Appliance Repair Services Suffolk County, NY | H3: =LEN(G3) -> 44 | I3: Browse all appliance repair services in Suffolk County, NY: refrigerators, washers, dryers, ovens, dishwashers and more. Call [PHONE]. | J3: =LEN(I3) -> 134 | K3: 800 | L3: 1200 | M3: 821 | N3: =IF(AND(M3>=K3,M3<=L3),"OK","Check") -> OK | O3: H1: Appliance Repair Services in Suffolk County, NY [BUSINESS NAME] repairs the appliances Suffolk County households and businesses rely on every day. Whether you need a quick fix for a refrigerator that won't cool or a specialist for a luxury range, our technicians diagnose the problem, explain your options and give you a firm price before any work begins. Choose an appliance below to learn about common problems, our repair process and the brands we service. Each service page also links to local pages for the towns we cover. H2: Core Appliance Repair H3: Refrigerator Repair A refrigerator that stops cooling puts hundreds of dollars of food at risk within hours, so fast and accurate diagnosis matters. We repair top-freezer, bottom-freezer, side-by-side, French-door and counter-depth models. Common issues include cooling, leaking and noise problems. H3: Freezer Repair Whether it is a chest freezer in the garage or an upright in the basement, a failing freezer can ruin weeks of groceries before you notice. We repair upright, chest, built-in and combination freezers. Common issues include warming, frost buildup and compressor problems. H3: Washing Machine Repair When your washing machine stops draining, spinning or filling, laundry day grinds to a halt. We repair top-load, front-load, high-efficiency and stackable washers. Common issues include leaks, drainage and spin problems. H3: Dryer Repair A dryer that takes two cycles to dry a load is wasting energy and can be a fire hazard. We repair gas and electric dryers, including stackable and ventless models. Common issues include no-heat, long drying times and noise. H3: Dishwasher Repair A dishwasher that leaves dishes dirty, leaks or never drains turns a daily convenience into a daily headache. We repair built-in, drawer and portable dishwashers. Common issues include leaks, drain issues and cleaning problems. H3: Oven Repair When your oven won't heat or bakes unevenly, dinner plans fall apart. We repair single and double wall ovens, electric and gas ovens and convection models. Common issues include heating, temperature and door problems. H3: Stove & Range Repair Your range is the workhorse of the kitchen, and a single failed burner or oven element can disrupt daily meals. We repair gas, electric, dual-fuel and induction stoves and ranges. Common issues include burner, igniter and oven problems. H3: Cooktop Repair Built-in cooktops are the centerpiece of many Suffolk County kitchens, and they need careful, brand-aware service. We repair gas, electric, radiant and induction cooktops. Common issues include burner, igniter and induction faults. H2: Specialty Appliance Repair H3: Microwave Repair Microwaves are used several times a day, so a unit that sparks, stops heating or won't start disrupts the kitchen quickly. We service countertop, over-the-range and built-in microwaves. Common issues include heating, display and door faults. H3: Ice Maker Repair A refrigerator ice maker or stand-alone ice machine that stops producing ice is a frequent complaint, especially in summer. We repair built-in, under-counter and refrigerator-mounted ice makers. Common issues include no ice, slow production and leaks. H3: Wine Cooler Repair Wine needs steady temperature and humidity, so even small cooling faults can harm a collection. We repair built-in, freestanding, dual-zone and under-counter wine coolers. Common issues include temperature, noise and compressor issues. H3: Garbage Disposal Repair A jammed or leaking garbage disposal can back up your kitchen sink and disrupt dishwasher drainage. We repair and replace continuous-feed and batch-feed disposals. Common issues include jams, leaks and motor failures. H3: Commercial Appliance Repair For restaurants, delis, cafes and shops, downtime costs money every hour. We repair commercial refrigeration, ranges, ovens, fryers, ice machines and other kitchen equipment. Common issues include refrigeration, cooking and ice equipment. H3: Luxury Appliance Repair Premium appliances demand technicians who understand their design and parts. We repair high-end refrigeration, ranges, wall ovens, cooktops and wine storage. Common issues include high-end refrigeration and cooking faults. H2: Local Service Pages We serve these Suffolk County towns, each with local information and repair pages for every service: - Appliance repair in Huntington, NY: Huntington Village, Huntington Station, Greenlawn, and Halesite - Appliance repair in Smithtown, NY: Smithtown, Kings Park, St. James, and Nesconset - Appliance repair in Islip, NY: Islip, East Islip, Islip Terrace, and Bay Shore - Appliance repair in Babylon, NY: Babylon Village, Lindenhurst, Copiague, and West Babylon - Appliance repair in Patchogue, NY: Patchogue Village, East Patchogue, North Patchogue, and Blue Point H2: How Our Service Works 1. Tell us what is wrong by phone or online. 2. We schedule an appointment window. 3. The technician diagnoses the fault and gives a quote. 4. You approve, we repair and test, and you receive a warranty. H2: Why Choose Us We are a local team focused on honest quotes, careful workmanship and clear communication. Our technicians service all major brands, and we explain every repair so you can make the right decision for your home. Call [PHONE] to book. H2: Not Sure What Service You Need? Describe the symptoms when you call and we will point you to the right service. Many problems, such as a dryer that won't heat or a washer that won't drain, have a quick fix. | P3: Refrigerator Repair -> /refrigerator-repair/ Freezer Repair -> /freezer-repair/ Washing Machine Repair -> /washer-repair/ Dryer Repair -> /dryer-repair/ Dishwasher Repair -> /dishwasher-repair/ Oven Repair -> /oven-repair/ Stove & Range Repair -> /stove-range-repair/ Cooktop Repair -> /cooktop-repair/ Microwave Repair -> /microwave-repair/ Ice Maker Repair -> /ice-maker-repair/ Wine Cooler Repair -> /wine-cooler-repair/ Garbage Disposal Repair -> /garbage-disposal-repair/ Commercial Appliance Repair -> /commercial-appliance-repair/ Luxury Appliance Repair -> /luxury-appliance-repair/ Appliance Repair Huntington -> /appliance-repair-huntington-ny/ Appliance Repair Smithtown -> /appliance-repair-smithtown-ny/ Appliance Repair Islip -> /appliance-repair-islip-ny/ Appliance Repair Babylon -> /appliance-repair-babylon-ny/ Appliance Repair Patchogue -> /appliance-repair-patchogue-ny/ Home -> / Contact Us -> /contact/ | Q3: =LEN(P3)-LEN(SUBSTITUTE(P3,CHAR(10),""))+1 -> 21 | R3: None | S3: Service (ItemList) | T3: To do
A4: 3 | B4: Main | C4: Trust | D4: About Us | E4: /about-us/ | F4: Appliance Repair Company Suffolk County NY | G4: About Us | Suffolk County Appliance Repair Company | H4: =LEN(G4) -> 50 | I4: Meet [BUSINESS NAME], a local Suffolk County appliance repair company with honest pricing and careful service. Call [PHONE]. | J4: =LEN(I4) -> 124 | K4: 300 | L4: 900 | M4: 438 | N4: =IF(AND(M4>=K4,M4<=L4),"OK","Check") -> OK | O4: H1: About [BUSINESS NAME] | Suffolk County Appliance Repair [BUSINESS NAME] is a local appliance repair company serving Suffolk County, Long Island. We started with a simple goal: fix appliances properly, price them honestly and treat every customer's home with respect. [INSERT YOUR STORY, YEARS IN BUSINESS AND FOUNDER NAME.] H2: What We Do We repair refrigerators, freezers, washers, dryers, dishwashers, ovens, stoves, cooktops, microwaves, ice makers, wine coolers, garbage disposals and commercial and luxury appliances for homes and businesses across Suffolk County. H2: Our Standards - Upfront pricing with no work begun until you approve. - Clear explanations of the fault and your options. - Honest advice on repair versus replacement. - Clean, respectful work in your home. - Warranty on parts and labor: [INSERT WARRANTY]. H2: Qualifications and Trust [INSERT LICENSES, INSURANCE, MANUFACTURER TRAINING, CERTIFICATIONS AND ANY AFFILIATIONS. Only list credentials you actually hold.] H2: Where We Work We serve Huntington, Smithtown, Islip, Babylon, Patchogue and neighboring communities across Suffolk County. See our service areas page for the full list. H2: Meet the Team [INSERT TECHNICIAN NAMES, PHOTOS AND EXPERIENCE.] H2: Get in Touch Call [PHONE] or request service online. We look forward to helping you. H2: How We Diagnose Problems A good repair starts with a correct diagnosis. We ask about symptoms, check error codes, test components with the right meters and tools, and confirm the root cause before suggesting parts. This prevents unnecessary replacements and repeat visits. H2: Our Promise We treat your home as we would our own: shoe covers when needed, tidy work areas and a clean finish. We explain what we found in plain language and let you decide. If a repair is not worthwhile, we tell you. H2: Serving Our Community We are proud to serve Suffolk County households and businesses, from North Shore homes to South Shore condos. Many of our customers are repeat clients and neighbors who recommend us to friends and family. H2: Parts and Quality We use OEM or high-quality equivalent parts and explain the options before installing them. Every repair is tested before we leave, and we stand behind the work with our warranty: [INSERT WARRANTY]. H2: Training and Continuing Education [INSERT ANY MANUFACTURER OR INDUSTRY TRAINING YOUR TECHNICIANS HAVE COMPLETED.] Appliances change every year, with more electronics, sensors and smart features, so ongoing training matters. We invest in diagnostic tools and keep up with common failure patterns across the brands we repair. H2: Residential and Commercial Experience Our work spans family kitchens, rental properties, condos and local businesses. That range means we understand both the needs of a homeowner who wants a quick, fair repair and a restaurant owner who needs equipment back up fast. [ADD EXAMPLES OF REAL PROJECTS OR CUSTOMER TYPES.] | P4: All Services -> /appliance-repair-services/ Service Areas -> /service-areas/ Reviews -> /reviews/ Contact Us -> /contact/ | Q4: =LEN(P4)-LEN(SUBSTITUTE(P4,CHAR(10),""))+1 -> 4 | R4: None | S4: AboutPage | T4: To do
A5: 4 | B5: Main | C5: Trust | D5: Contact Us | E5: /contact/ | F5: Contact Appliance Repair Suffolk County NY | G5: Contact Appliance Repair | Suffolk County, NY | H5: =LEN(G5) -> 45 | I5: Book an appliance repair in Suffolk County, NY. Call [PHONE] or request service online. Huntington, Smithtown, Islip, Babylon, Patchogue. | J5: =LEN(I5) -> 137 | K5: 300 | L5: 900 | M5: 336 | N5: =IF(AND(M5>=K5,M5<=L5),"OK","Check") -> OK | O5: H1: Contact [BUSINESS NAME] | Appliance Repair in Suffolk County Need an appliance repair technician in Suffolk County? Call [PHONE] or fill out the form below and we will get back to you as soon as possible. H2: Phone and Email Phone: [PHONE] Email: [INSERT EMAIL] Service hours: [INSERT HOURS] H2: Request a Repair Tell us the appliance type, brand and model, a brief description of the problem and your town. Include any error codes shown on the display. H2: Service Area We serve Suffolk County including Huntington, Smithtown, Islip, Babylon and Patchogue. Not sure if we cover your address? Ask and we will confirm. H2: Business Address [INSERT ADDRESS IF CUSTOMERS MAY VISIT; OTHERWISE STATE THAT WE ARE A SERVICE-AREA BUSINESS.] H2: What to Have Ready - Appliance brand and model number. - A short description of the symptoms. - Your preferred appointment times. H2: How Booking Works Submit the form or call us. We confirm your address, ask a few questions about the appliance and offer the earliest appointment window we can. A technician arrives, diagnoses the fault and gives a quote. You approve before any work begins. H2: Emergencies and After-Hours Requests [INSERT YOUR EMERGENCY OR AFTER-HOURS POLICY.] If you have a gas smell, leave the home and call your gas utility or emergency services first. If a water leak is flooding your home, shut off the supply valve. H2: Commercial Customers Restaurants, cafes and shops can request priority scheduling for refrigeration, ice machines and cooking equipment. Mention that you are a business when you contact us. H2: Tips for a Faster Repair Send a photo of the model label and of any error code on the display. Describe sounds, smells or leaks, and tell us when the problem started. The more detail we have before the visit, the more likely the technician arrives with the right parts. H2: Directions and Parking [INSERT PARKING OR ACCESS NOTES FOR TECHNICIANS, OR NOTE THAT WE TRAVEL TO YOU.] If you live in an apartment or condo building, tell us about building rules, elevator access or required insurance paperwork when booking. | P5: All Services -> /appliance-repair-services/ Service Areas -> /service-areas/ FAQs -> /frequently-asked-questions/ | Q5: =LEN(P5)-LEN(SUBSTITUTE(P5,CHAR(10),""))+1 -> 3 | R5: None | S5: ContactPage / LocalBusiness | T5: To do
A6: 5 | B6: Main | C6: Trust | D6: FAQs | E6: /frequently-asked-questions/ | F6: Appliance Repair FAQs Suffolk County NY | G6: Appliance Repair FAQs | Suffolk County, NY | H6: =LEN(G6) -> 42 | I6: Answers to common appliance repair questions in Suffolk County, NY: pricing, scheduling, brands, warranty and repair vs replace. | J6: =LEN(I6) -> 128 | K6: 300 | L6: 900 | M6: 542 | N6: =IF(AND(M6>=K6,M6<=L6),"OK","Check") -> OK | O6: H1: Appliance Repair FAQs | Suffolk County, NY Answers to the questions Suffolk County customers ask most often about our appliance repair services. Q: What areas of Suffolk County do you serve? A: We serve Huntington, Smithtown, Islip, Babylon, Patchogue and nearby communities. Contact us to confirm your address. Q: How do I book a repair? A: Call us or use the online form. Tell us the appliance, the symptoms and your town. Q: Do you charge a diagnostic fee? A: [INSERT YOUR DIAGNOSTIC FEE POLICY]. Q: Will you give me a price before starting? A: Yes. You receive a written quote and nothing begins until you agree. Q: How fast can you come? A: [INSERT SAME-DAY / NEXT-DAY POLICY]. Q: Which brands do you repair? A: Most major brands including Whirlpool, GE, Samsung, LG, Frigidaire, Maytag, KitchenAid, Bosch, Sub-Zero, Wolf and Viking. Q: Do you repair commercial appliances? A: Yes, including refrigeration, ice machines and cooking equipment. Q: Should I repair or replace my appliance? A: Generally, repair when the unit is relatively new and the fault is a common part. For older units with major failures, replacement may be better. We give honest advice. Q: Do you warranty your repairs? A: Yes. [INSERT WARRANTY TERMS]. Q: Do you supply and install parts? A: Yes. We use OEM or equivalent parts and explain options. Q: What payment methods do you accept? A: [INSERT PAYMENT METHODS]. Q: Do you remove old appliances? A: [INSERT YOUR POLICY]. Still have questions? Call [PHONE]. H2: More Questions Q: Can I get an estimate over the phone? A: We can describe common causes and general ranges where possible, but the firm price comes after a technician diagnoses the appliance. Q: Do you work on built-in and integrated appliances? A: Yes. We service built-in, panel-ready and integrated models, including premium brands. Q: What should I do before the technician arrives? A: Clear the area, note error codes and keep the model number handy. If there is a leak, shut off power and water where safe. Q: What if the part is not in stock? A: We will explain the lead time and options, and schedule a return visit once the part arrives. H2: Repair Costs Q: Why do repair prices vary? A: Price depends on the fault, the part, the brand and the labor involved. This is why we diagnose first and give you a written quote. Q: Do you charge for estimates on replacements? A: [INSERT YOUR POLICY]. H2: About Our Technicians Q: Are your technicians licensed and insured? A: [INSERT LICENSING AND INSURANCE DETAILS]. Q: Will someone be home during the repair? A: An adult should be present, or arrangements should be made in advance for access. Q: Do you provide receipts and invoices? A: Yes, every completed job includes an itemized invoice with warranty details. H2: Safety Questions Q: What should I do if I smell gas? A: Leave the home immediately, avoid switches and flames, and call your gas utility or emergency services from outside. Q: Is it safe to use an appliance that is leaking? A: No. Turn off power and water where safe and call us. Q: Can a clogged dryer vent be dangerous? A: Yes. Lint buildup is a known fire hazard, so have vents cleaned regularly. | P6: All Services -> /appliance-repair-services/ Brands We Service -> /appliance-brands/ Contact Us -> /contact/ | Q6: =LEN(P6)-LEN(SUBSTITUTE(P6,CHAR(10),""))+1 -> 3 | R6: None | S6: FAQPage | T6: To do
A7: 6 | B7: Core Service | C7: Refrigerator Repair | D7: Refrigerator Repair | E7: /refrigerator-repair/ | F7: Refrigerator Repair Suffolk County NY | G7: Refrigerator Repair Suffolk County, NY | [BUSINESS NAME] | H7: =LEN(G7) -> 56 | I7: Need refrigerator repair in Suffolk County, NY? Local technicians fix cooling, leaking and noise problems with upfront quotes. Call [PHONE] to book. | J7: =LEN(I7) -> 148 | K7: 800 | L7: 1200 | M7: 1106 | N7: =IF(AND(M7>=K7,M7<=L7),"OK","Check") -> OK | O7: H1: Refrigerator Repair in Suffolk County, NY A refrigerator that stops cooling puts hundreds of dollars of food at risk within hours, so fast and accurate diagnosis matters. We repair top-freezer, bottom-freezer, side-by-side, French-door and counter-depth models. [BUSINESS NAME] serves homeowners and businesses across Suffolk County, including Huntington, Smithtown, Islip, Babylon and Patchogue, with clear upfront pricing and no work started until you approve the quote. If you are searching for refrigerator repair near you, our technicians diagnose the real cause instead of guessing, which saves you from paying for parts you don't need. Call [PHONE] or request a visit online to get started. H2: Signs Your Refrigerator Needs Repair Appliances rarely fail without warning. These are the most common refrigerator problems we see across Suffolk County and what usually causes them: H3: Not cooling or too warm Often caused by a failed evaporator fan motor, a dirty condenser coil, a faulty defrost system or a sealed-system issue. H3: Freezer works but the fridge section is warm Usually points to a blocked air damper, a failed evaporator fan or a frozen evaporator coil restricting airflow. H3: Water leaking onto the floor Typically a clogged defrost drain, a cracked water line or a failed inlet valve on models with a water dispenser. H3: Loud buzzing, clicking or rattling Fan motors wearing out, or a compressor start relay that clicks repeatedly without starting the compressor. H3: Frost or ice buildup Suggests a failed defrost heater, defrost thermostat or control board interrupting the defrost cycle. H3: Running constantly Dirty condenser coils, a worn door gasket or a failing temperature sensor can keep the compressor running non-stop. H2: Our Refrigerator Repair Process Our technician checks temperatures, airflow, coils, fans, gaskets and the defrost system, explains the cause in plain language and gives a clear price before starting. Common replacement parts are often carried on the service vehicle, so many repairs can be finished in a single visit. 1. Book your visit by phone or online and tell us the brand, model and symptoms. 2. A technician arrives within the appointment window and inspects the refrigerator. 3. You receive a clear explanation of the fault and a firm price before any work begins. 4. We complete the repair, test the appliance and show you the result. 5. You receive a written invoice and our warranty details: [INSERT PARTS AND LABOR WARRANTY]. H2: Parts We Replace Most Often For refrigerator repairs, the parts we replace most often include evaporator and condenser fan motors, defrost heaters, thermostats, start relays, door gaskets and water inlet valves. We use quality OEM or equivalent parts, and we explain which options are available when more than one exists. H2: Brands We Service We repair refrigerator models from Whirlpool, GE, Samsung, LG, Frigidaire, KitchenAid, Maytag, Bosch, Sub-Zero, Viking, Thermador, and Electrolux, along with many others. Not sure whether your model is covered? Tell us the brand and model number from the label and we will confirm before booking. H2: Should You Repair or Replace Your Refrigerator? If the unit is 12 to 15 years old and needs a sealed-system repair, replacement is often more economical. For newer units, or for parts such as fans, sensors and defrost components, repair usually makes more sense. Factors that help you decide include the age of the unit, the cost of the repair compared with a new appliance, how often it has broken down and how efficient it is compared with newer models. We give you an honest recommendation, even when that means telling you not to repair it. H2: What Affects the Cost of Refrigerator Repair The final price depends on the diagnosis, the part needed, the brand and how hard the appliance is to access. Rather than quoting a vague range over the phone, we diagnose first, give you a firm written price and wait for your approval. Diagnostic fee: [INSERT DIAGNOSTIC FEE, CREDITED TOWARD REPAIR IF APPLICABLE]. H2: Maintenance Tips to Prevent Future Breakdowns - Vacuum the condenser coils every six to twelve months. - Keep the refrigerator near 37 to 40°F and the freezer at 0°F. - Test the door gasket by closing a dollar bill in the door; it should resist being pulled out. - Leave a few inches of clearance behind and above the unit for airflow. Safety note: Move perishables into a cooler with ice and keep the doors closed while you wait for service. H2: Why Suffolk County Customers Choose [BUSINESS NAME] We are a local team that knows Long Island homes, from older North Shore houses to South Shore condos and apartments. Our technicians are [INSERT LICENSING / INSURANCE DETAILS], and we aim to show up on time, keep your home clean and explain every step in plain English. Customers value honest quotes, tidy work and repairs that last. H2: Refrigerator Repair Near You We provide service in these areas, each with its own local page: - Refrigerator Repair in Huntington, NY - Refrigerator Repair in Smithtown, NY - Refrigerator Repair in Islip, NY - Refrigerator Repair in Babylon, NY - Refrigerator Repair in Patchogue, NY If your neighborhood is not listed, contact us. We may still be able to help, depending on your location. H2: Frequently Asked Questions Q: How long is food safe if my refrigerator stops cooling? A: Food safety guidance says a closed refrigerator keeps food cold for about four hours during a power outage. If your unit is simply not cooling, call promptly and move perishables to a cooler. Q: Is it worth repairing a refrigerator? A: In most cases repair is worthwhile when the unit is under about ten years old and the fault is a fan, sensor, relay or defrost part. We will tell you honestly if replacement is the better value. Q: Why is my refrigerator leaking water? A: The usual causes are a frozen or clogged defrost drain, a loose water line or a faulty inlet valve. Unplugging the unit and mopping up the water protects your floors until we arrive. Q: How much does refrigerator repair cost in Suffolk County? A: The cost depends on the fault, the part and the brand. We diagnose the problem first and give a written quote so you know the price before work begins. Q: How quickly can you schedule refrigerator repair? A: Availability varies by day and location. [INSERT YOUR SAME-DAY / NEXT-DAY POLICY HERE]. Call us and we will offer the earliest appointment window. Q: Do you guarantee your repairs? A: Yes. We back our work with a [INSERT WARRANTY LENGTH] parts and labor warranty, so you are covered if the same problem returns. H2: Schedule Your Refrigerator Repair Today Don't live with a broken refrigerator. Call [PHONE] or use our online booking form to schedule a technician anywhere in Suffolk County. | P7: All Services -> /appliance-repair-services/ Freezer Repair -> /freezer-repair/ Ice Maker Repair -> /ice-maker-repair/ Wine Cooler Repair -> /wine-cooler-repair/ Refrigerator Repair in Huntington, NY -> /refrigerator-repair/huntington-ny/ Refrigerator Repair in Smithtown, NY -> /refrigerator-repair/smithtown-ny/ Refrigerator Repair in Islip, NY -> /refrigerator-repair/islip-ny/ Refrigerator Repair in Babylon, NY -> /refrigerator-repair/babylon-ny/ Refrigerator Repair in Patchogue, NY -> /refrigerator-repair/patchogue-ny/ Brands We Service -> /appliance-brands/ Service Areas -> /service-areas/ Contact Us -> /contact/ Reviews -> /reviews/ | Q7: =LEN(P7)-LEN(SUBSTITUTE(P7,CHAR(10),""))+1 -> 13 | R7: FoodSafety.gov refrigerator and freezer guidance -> https://www.foodsafety.gov/ ENERGY STAR certified products -> https://www.energystar.gov/products | S7: Service | T7: To do
A8: 7 | B8: Core Service | C8: Freezer Repair | D8: Freezer Repair | E8: /freezer-repair/ | F8: Freezer Repair Suffolk County NY | G8: Freezer Repair Suffolk County, NY | [BUSINESS NAME] | H8: =LEN(G8) -> 51 | I8: Need freezer repair in Suffolk County, NY? Local technicians fix warming, frost buildup and compressor problems with upfront quotes. Call [PHONE] to book. | J8: =LEN(I8) -> 154 | K8: 800 | L8: 1200 | M8: 1026 | N8: =IF(AND(M8>=K8,M8<=L8),"OK","Check") -> OK | O8: H1: Freezer Repair in Suffolk County, NY Whether it is a chest freezer in the garage or an upright in the basement, a failing freezer can ruin weeks of groceries before you notice. We repair upright, chest, built-in and combination freezers. [BUSINESS NAME] serves homeowners and businesses across Suffolk County, including Huntington, Smithtown, Islip, Babylon and Patchogue, with clear upfront pricing and no work started until you approve the quote. If you are searching for freezer repair near you, our technicians diagnose the real cause instead of guessing, which saves you from paying for parts you don't need. Call [PHONE] or request a visit online to get started. H2: Signs Your Freezer Needs Repair Appliances rarely fail without warning. These are the most common freezer problems we see across Suffolk County and what usually causes them: H3: Not freezing or temperature creeping up A failing compressor, start relay, evaporator fan or thermostat can stop the freezer from holding 0°F. H3: Heavy frost or ice buildup A worn door gasket, a door left ajar or a failed defrost heater lets moist air in and coats the coils. H3: Constant running Dirty condenser coils, low refrigerant or a faulty temperature control force the compressor to run non-stop. H3: Noisy operation Buzzing, grinding or clicking often means a fan motor, compressor mount or start relay is wearing out. H3: Water pooling under the unit Clogged defrost drains, or melting frost from a failed defrost cycle, can leak onto the floor. H3: Freezer burn on food Temperature swings from a weak thermostat or poor door seal degrade stored food quickly. H2: Our Freezer Repair Process We check temperature, airflow, gaskets, fans and the defrost system, confirm whether the sealed system is involved and quote the repair before any work begins. You approve the price first, every time. 1. Book your visit by phone or online and tell us the brand, model and symptoms. 2. A technician arrives within the appointment window and inspects the freezer. 3. You receive a clear explanation of the fault and a firm price before any work begins. 4. We complete the repair, test the appliance and show you the result. 5. You receive a written invoice and our warranty details: [INSERT PARTS AND LABOR WARRANTY]. H2: Parts We Replace Most Often For freezer repairs, the parts we replace most often include thermostats, start relays, evaporator fan motors, defrost heaters and door gaskets. We use quality OEM or equivalent parts, and we explain which options are available when more than one exists. H2: Brands We Service We repair freezer models from Frigidaire, GE, Whirlpool, Kenmore, Electrolux, Haier, Danby, Amana, Maytag, and Samsung, along with many others. Not sure whether your model is covered? Tell us the brand and model number from the label and we will confirm before booking. H2: Should You Repair or Replace Your Freezer? Freezers commonly last 10 to 20 years, so an older unit needing a compressor or sealed-system repair is often better replaced, while fans, relays, thermostats and gaskets are worthwhile repairs. Factors that help you decide include the age of the unit, the cost of the repair compared with a new appliance, how often it has broken down and how efficient it is compared with newer models. We give you an honest recommendation, even when that means telling you not to repair it. H2: What Affects the Cost of Freezer Repair The final price depends on the diagnosis, the part needed, the brand and how hard the appliance is to access. Rather than quoting a vague range over the phone, we diagnose first, give you a firm written price and wait for your approval. Diagnostic fee: [INSERT DIAGNOSTIC FEE, CREDITED TOWARD REPAIR IF APPLICABLE]. H2: Maintenance Tips to Prevent Future Breakdowns - Defrost manual-defrost chest freezers when frost reaches about a quarter inch. - Keep the freezer roughly three-quarters full so it holds temperature more efficiently. - Clean condenser coils twice a year. - Avoid overloading door shelves, which can break gasket seals. Safety note: Keep the lid or door shut and group food together to slow thawing while you wait for service. H2: Why Suffolk County Customers Choose [BUSINESS NAME] We are a local team that knows Long Island homes, from older North Shore houses to South Shore condos and apartments. Our technicians are [INSERT LICENSING / INSURANCE DETAILS], and we aim to show up on time, keep your home clean and explain every step in plain English. Customers value honest quotes, tidy work and repairs that last. H2: Freezer Repair Near You We provide service in these areas, each with its own local page: - Freezer Repair in Huntington, NY - Freezer Repair in Smithtown, NY - Freezer Repair in Islip, NY - Freezer Repair in Babylon, NY - Freezer Repair in Patchogue, NY If your neighborhood is not listed, contact us. We may still be able to help, depending on your location. H2: Frequently Asked Questions Q: How long does food stay frozen if my freezer stops working? A: Food safety guidance says a full freezer that stays closed holds temperature for roughly 48 hours and a half-full one for about 24 hours, so call as soon as you notice a problem. Q: Why is my freezer covered in frost? A: Usually a door seal leak or a defrost system fault. Replacing a worn gasket or defrost component normally clears the problem. Q: Can you repair both chest and upright freezers? A: Yes. We service chest, upright, built-in and under-counter freezers from all major brands. Q: How much does freezer repair cost in Suffolk County? A: The cost depends on the fault, the part and the brand. We diagnose the problem first and give a written quote so you know the price before work begins. Q: How quickly can you schedule freezer repair? A: Availability varies by day and location. [INSERT YOUR SAME-DAY / NEXT-DAY POLICY HERE]. Call us and we will offer the earliest appointment window. Q: Do you guarantee your repairs? A: Yes. We back our work with a [INSERT WARRANTY LENGTH] parts and labor warranty, so you are covered if the same problem returns. H2: Schedule Your Freezer Repair Today Don't live with a broken freezer. Call [PHONE] or use our online booking form to schedule a technician anywhere in Suffolk County. | P8: All Services -> /appliance-repair-services/ Refrigerator Repair -> /refrigerator-repair/ Ice Maker Repair -> /ice-maker-repair/ Commercial Appliance Repair -> /commercial-appliance-repair/ Freezer Repair in Huntington, NY -> /freezer-repair/huntington-ny/ Freezer Repair in Smithtown, NY -> /freezer-repair/smithtown-ny/ Freezer Repair in Islip, NY -> /freezer-repair/islip-ny/ Freezer Repair in Babylon, NY -> /freezer-repair/babylon-ny/ Freezer Repair in Patchogue, NY -> /freezer-repair/patchogue-ny/ Brands We Service -> /appliance-brands/ Service Areas -> /service-areas/ Contact Us -> /contact/ Reviews -> /reviews/ | Q8: =LEN(P8)-LEN(SUBSTITUTE(P8,CHAR(10),""))+1 -> 13 | R8: FoodSafety.gov refrigerator and freezer guidance -> https://www.foodsafety.gov/ ENERGY STAR certified products -> https://www.energystar.gov/products | S8: Service | T8: To do
A9: 8 | B9: Core Service | C9: Washing Machine Repair | D9: Washing Machine Repair | E9: /washer-repair/ | F9: Washing Machine Repair Suffolk County NY | G9: Washing Machine Repair Suffolk County, NY | [BUSINESS NAME] | H9: =LEN(G9) -> 59 | I9: Need washing machine repair in Suffolk County, NY? Local technicians fix leaks, drainage and spin problems with upfront quotes. Call [PHONE] to book. | J9: =LEN(I9) -> 149 | K9: 800 | L9: 1200 | M9: 1032 | N9: =IF(AND(M9>=K9,M9<=L9),"OK","Check") -> OK | O9: H1: Washing Machine Repair in Suffolk County, NY When your washing machine stops draining, spinning or filling, laundry day grinds to a halt. We repair top-load, front-load, high-efficiency and stackable washers. [BUSINESS NAME] serves homeowners and businesses across Suffolk County, including Huntington, Smithtown, Islip, Babylon and Patchogue, with clear upfront pricing and no work started until you approve the quote. If you are searching for washing machine repair near you, our technicians diagnose the real cause instead of guessing, which saves you from paying for parts you don't need. Call [PHONE] or request a visit online to get started. H2: Signs Your Washer Needs Repair Appliances rarely fail without warning. These are the most common washer problems we see across Suffolk County and what usually causes them: H3: Won't drain or leaves water in the drum A clogged drain pump filter, failed drain pump or kinked drain hose is the usual culprit. H3: Won't spin or spins weakly Worn drive belts, a faulty lid switch or door lock, a failing motor coupling or an out-of-balance load. H3: Leaking water Worn door boot seals, loose hoses, a cracked pump housing or a failing water inlet valve. H3: Loud banging or grinding Worn tub bearings, damaged shock absorbers or suspension rods, or a loose drum. H3: Won't start or fill A bad door latch, lid switch, water inlet valve or control board can stop the cycle before it begins. H3: Musty odor Mold and residue buildup in the door seal and detergent drawer, often made worse by low-temperature washing. H2: Our Washer Repair Process We run the machine through its cycles, inspect the pump, hoses, seals, suspension and controls, then explain the fault and give a firm price. If a repair is not worthwhile, we will say so. 1. Book your visit by phone or online and tell us the brand, model and symptoms. 2. A technician arrives within the appointment window and inspects the washer. 3. You receive a clear explanation of the fault and a firm price before any work begins. 4. We complete the repair, test the appliance and show you the result. 5. You receive a written invoice and our warranty details: [INSERT PARTS AND LABOR WARRANTY]. H2: Parts We Replace Most Often For washer repairs, the parts we replace most often include drain pumps, door boot seals, water inlet valves, lid and door switches, drive belts, shock absorbers and bearings. We use quality OEM or equivalent parts, and we explain which options are available when more than one exists. H2: Brands We Service We repair washer models from Whirlpool, Maytag, GE, Samsung, LG, Electrolux, Bosch, Speed Queen, Frigidaire, Kenmore, and Amana, along with many others. Not sure whether your model is covered? Tell us the brand and model number from the label and we will confirm before booking. H2: Should You Repair or Replace Your Washer? Washers typically last 10 to 14 years. Bearing and tub failures on older machines often cost more than they are worth, while pumps, switches, belts and valves are usually sound repairs. Factors that help you decide include the age of the unit, the cost of the repair compared with a new appliance, how often it has broken down and how efficient it is compared with newer models. We give you an honest recommendation, even when that means telling you not to repair it. H2: What Affects the Cost of Washing Machine Repair The final price depends on the diagnosis, the part needed, the brand and how hard the appliance is to access. Rather than quoting a vague range over the phone, we diagnose first, give you a firm written price and wait for your approval. Diagnostic fee: [INSERT DIAGNOSTIC FEE, CREDITED TOWARD REPAIR IF APPLICABLE]. H2: Maintenance Tips to Prevent Future Breakdowns - Leave the door ajar after each wash so the drum can dry. - Clean the drain pump filter every few months on front-loaders. - Use the recommended amount of HE detergent only. - Replace rubber fill hoses every five years to prevent bursts. Safety note: Turn off the water supply valves and unplug the washer if you see leaking or smell burning. H2: Why Suffolk County Customers Choose [BUSINESS NAME] We are a local team that knows Long Island homes, from older North Shore houses to South Shore condos and apartments. Our technicians are [INSERT LICENSING / INSURANCE DETAILS], and we aim to show up on time, keep your home clean and explain every step in plain English. Customers value honest quotes, tidy work and repairs that last. H2: Washing Machine Repair Near You We provide service in these areas, each with its own local page: - Washing Machine Repair in Huntington, NY - Washing Machine Repair in Smithtown, NY - Washing Machine Repair in Islip, NY - Washing Machine Repair in Babylon, NY - Washing Machine Repair in Patchogue, NY If your neighborhood is not listed, contact us. We may still be able to help, depending on your location. H2: Frequently Asked Questions Q: Why is my washing machine not draining? A: A blocked pump filter or hose, or a failed drain pump, is the most common cause. A technician can clear or replace these quickly. Q: Is it worth fixing a washing machine? A: Usually yes if it is under eight years old and the fault is a pump, valve, switch or belt. We compare repair cost against replacement so you can decide. Q: Can you repair front-load and top-load washers? A: Yes. We service front-load, top-load, HE and stackable washers from major brands. Q: How much does washing machine repair cost in Suffolk County? A: The cost depends on the fault, the part and the brand. We diagnose the problem first and give a written quote so you know the price before work begins. Q: How quickly can you schedule washing machine repair? A: Availability varies by day and location. [INSERT YOUR SAME-DAY / NEXT-DAY POLICY HERE]. Call us and we will offer the earliest appointment window. Q: Do you guarantee your repairs? A: Yes. We back our work with a [INSERT WARRANTY LENGTH] parts and labor warranty, so you are covered if the same problem returns. H2: Schedule Your Washing Machine Repair Today Don't live with a broken washer. Call [PHONE] or use our online booking form to schedule a technician anywhere in Suffolk County. | P9: All Services -> /appliance-repair-services/ Dryer Repair -> /dryer-repair/ Dishwasher Repair -> /dishwasher-repair/ Refrigerator Repair -> /refrigerator-repair/ Washing Machine Repair in Huntington, NY -> /washer-repair/huntington-ny/ Washing Machine Repair in Smithtown, NY -> /washer-repair/smithtown-ny/ Washing Machine Repair in Islip, NY -> /washer-repair/islip-ny/ Washing Machine Repair in Babylon, NY -> /washer-repair/babylon-ny/ Washing Machine Repair in Patchogue, NY -> /washer-repair/patchogue-ny/ Brands We Service -> /appliance-brands/ Service Areas -> /service-areas/ Contact Us -> /contact/ Reviews -> /reviews/ | Q9: =LEN(P9)-LEN(SUBSTITUTE(P9,CHAR(10),""))+1 -> 13 | R9: U.S. Consumer Product Safety Commission -> https://www.cpsc.gov/ ENERGY STAR certified products -> https://www.energystar.gov/products | S9: Service | T9: To do
A10: 9 | B10: Core Service | C10: Dryer Repair | D10: Dryer Repair | E10: /dryer-repair/ | F10: Dryer Repair Suffolk County NY | G10: Dryer Repair Suffolk County, NY | [BUSINESS NAME] | H10: =LEN(G10) -> 49 | I10: Need dryer repair in Suffolk County, NY? Local technicians fix no-heat, long drying times and noise with upfront quotes. Call [PHONE] to book. | J10: =LEN(I10) -> 142 | K10: 800 | L10: 1200 | M10: 1005 | N10: =IF(AND(M10>=K10,M10<=L10),"OK","Check") -> OK | O10: H1: Dryer Repair in Suffolk County, NY A dryer that takes two cycles to dry a load is wasting energy and can be a fire hazard. We repair gas and electric dryers, including stackable and ventless models. [BUSINESS NAME] serves homeowners and businesses across Suffolk County, including Huntington, Smithtown, Islip, Babylon and Patchogue, with clear upfront pricing and no work started until you approve the quote. If you are searching for dryer repair near you, our technicians diagnose the real cause instead of guessing, which saves you from paying for parts you don't need. Call [PHONE] or request a visit online to get started. H2: Signs Your Dryer Needs Repair Appliances rarely fail without warning. These are the most common dryer problems we see across Suffolk County and what usually causes them: H3: No heat A failed heating element, thermal fuse, gas igniter or thermostat is the usual cause. H3: Takes too long to dry Clogged lint screens and vent lines are common, along with weak heating components or a failing thermostat. H3: Won't start A blown thermal fuse, faulty start switch, door switch or motor can leave the dryer dead. H3: Drum won't turn A broken drive belt, worn idler pulley or failing motor stops the drum from rotating. H3: Loud thumping, squealing or scraping Worn drum rollers, glides, belts or bearings. H3: Burning smell or very hot exterior Restricted airflow or lint buildup, which should be addressed immediately. H2: Our Dryer Repair Process We test heat, airflow and electrical components, check the vent run for restrictions and replace failed parts. Because blocked vents cause many failures, we point out any airflow problems we find. 1. Book your visit by phone or online and tell us the brand, model and symptoms. 2. A technician arrives within the appointment window and inspects the dryer. 3. You receive a clear explanation of the fault and a firm price before any work begins. 4. We complete the repair, test the appliance and show you the result. 5. You receive a written invoice and our warranty details: [INSERT PARTS AND LABOR WARRANTY]. H2: Parts We Replace Most Often For dryer repairs, the parts we replace most often include heating elements, thermal fuses, gas igniters, belts, drum rollers, idler pulleys and door switches. We use quality OEM or equivalent parts, and we explain which options are available when more than one exists. H2: Brands We Service We repair dryer models from Whirlpool, Maytag, GE, Samsung, LG, Electrolux, Frigidaire, Kenmore, Speed Queen, Amana, and Bosch, along with many others. Not sure whether your model is covered? Tell us the brand and model number from the label and we will confirm before booking. H2: Should You Repair or Replace Your Dryer? Dryers often last 10 to 13 years. Simple, inexpensive parts such as fuses, belts and elements make repair a good value, while major motor or control failures on very old units may not. Factors that help you decide include the age of the unit, the cost of the repair compared with a new appliance, how often it has broken down and how efficient it is compared with newer models. We give you an honest recommendation, even when that means telling you not to repair it. H2: What Affects the Cost of Dryer Repair The final price depends on the diagnosis, the part needed, the brand and how hard the appliance is to access. Rather than quoting a vague range over the phone, we diagnose first, give you a firm written price and wait for your approval. Diagnostic fee: [INSERT DIAGNOSTIC FEE, CREDITED TOWARD REPAIR IF APPLICABLE]. H2: Maintenance Tips to Prevent Future Breakdowns - Clean the lint screen after every load. - Have the vent line cleaned once a year, or more often with long vent runs. - Do not run the dryer when no one is home. - Never overload the drum, which strains the motor and belt. Safety note: Stop using the dryer immediately if you notice a burning smell, and clear the lint screen. H2: Why Suffolk County Customers Choose [BUSINESS NAME] We are a local team that knows Long Island homes, from older North Shore houses to South Shore condos and apartments. Our technicians are [INSERT LICENSING / INSURANCE DETAILS], and we aim to show up on time, keep your home clean and explain every step in plain English. Customers value honest quotes, tidy work and repairs that last. H2: Dryer Repair Near You We provide service in these areas, each with its own local page: - Dryer Repair in Huntington, NY - Dryer Repair in Smithtown, NY - Dryer Repair in Islip, NY - Dryer Repair in Babylon, NY - Dryer Repair in Patchogue, NY If your neighborhood is not listed, contact us. We may still be able to help, depending on your location. H2: Frequently Asked Questions Q: Why is my dryer running but not heating? A: In electric dryers it is often the heating element or thermal fuse; in gas dryers it is typically the igniter or gas valve coils. Q: Why does my dryer take so long to dry clothes? A: Restricted airflow from lint in the vent line is the most common reason, followed by a weak heating element or thermostat. Q: Can a clogged dryer vent cause a fire? A: Yes. Lint buildup is a leading cause of dryer fires, which is why regular vent cleaning is strongly recommended. Q: How much does dryer repair cost in Suffolk County? A: The cost depends on the fault, the part and the brand. We diagnose the problem first and give a written quote so you know the price before work begins. Q: How quickly can you schedule dryer repair? A: Availability varies by day and location. [INSERT YOUR SAME-DAY / NEXT-DAY POLICY HERE]. Call us and we will offer the earliest appointment window. Q: Do you guarantee your repairs? A: Yes. We back our work with a [INSERT WARRANTY LENGTH] parts and labor warranty, so you are covered if the same problem returns. H2: Schedule Your Dryer Repair Today Don't live with a broken dryer. Call [PHONE] or use our online booking form to schedule a technician anywhere in Suffolk County. | P10: All Services -> /appliance-repair-services/ Washing Machine Repair -> /washer-repair/ Dishwasher Repair -> /dishwasher-repair/ Stove & Range Repair -> /stove-range-repair/ Dryer Repair in Huntington, NY -> /dryer-repair/huntington-ny/ Dryer Repair in Smithtown, NY -> /dryer-repair/smithtown-ny/ Dryer Repair in Islip, NY -> /dryer-repair/islip-ny/ Dryer Repair in Babylon, NY -> /dryer-repair/babylon-ny/ Dryer Repair in Patchogue, NY -> /dryer-repair/patchogue-ny/ Brands We Service -> /appliance-brands/ Service Areas -> /service-areas/ Contact Us -> /contact/ Reviews -> /reviews/ | Q10: =LEN(P10)-LEN(SUBSTITUTE(P10,CHAR(10),""))+1 -> 13 | R10: U.S. Consumer Product Safety Commission -> https://www.cpsc.gov/ ENERGY STAR certified products -> https://www.energystar.gov/products | S10: Service | T10: To do
A11: 10 | B11: Core Service | C11: Dishwasher Repair | D11: Dishwasher Repair | E11: /dishwasher-repair/ | F11: Dishwasher Repair Suffolk County NY | G11: Dishwasher Repair Suffolk County, NY | [BUSINESS NAME] | H11: =LEN(G11) -> 54 | I11: Need dishwasher repair in Suffolk County, NY? Local technicians fix leaks, drain issues and cleaning problems with upfront quotes. Call [PHONE] to book. | J11: =LEN(I11) -> 152 | K11: 800 | L11: 1200 | M11: 963 | N11: =IF(AND(M11>=K11,M11<=L11),"OK","Check") -> OK | O11: H1: Dishwasher Repair in Suffolk County, NY A dishwasher that leaves dishes dirty, leaks or never drains turns a daily convenience into a daily headache. We repair built-in, drawer and portable dishwashers. [BUSINESS NAME] serves homeowners and businesses across Suffolk County, including Huntington, Smithtown, Islip, Babylon and Patchogue, with clear upfront pricing and no work started until you approve the quote. If you are searching for dishwasher repair near you, our technicians diagnose the real cause instead of guessing, which saves you from paying for parts you don't need. Call [PHONE] or request a visit online to get started. H2: Signs Your Dishwasher Needs Repair Appliances rarely fail without warning. These are the most common dishwasher problems we see across Suffolk County and what usually causes them: H3: Not draining A clogged filter, kinked drain hose, blocked disposal connection or failed drain pump. H3: Dishes not coming out clean Clogged spray arms, a dirty filter, a weak circulation pump or a failed inlet valve. H3: Leaking from the door or base A worn door gasket, loose hose clamp, cracked sump or failed pump seal. H3: Won't start or latch A broken door latch, faulty control board or failed switch. H3: Won't dry dishes A failed heating element, vent fan issue or empty rinse-aid dispenser. H3: Strange noises Worn pump bearings, a loose spray arm or debris caught in the pump. H2: Our Dishwasher Repair Process We inspect the filter, spray arms, pump, hoses, door seal and controls, run a test cycle to reproduce the fault and quote the repair before starting. 1. Book your visit by phone or online and tell us the brand, model and symptoms. 2. A technician arrives within the appointment window and inspects the dishwasher. 3. You receive a clear explanation of the fault and a firm price before any work begins. 4. We complete the repair, test the appliance and show you the result. 5. You receive a written invoice and our warranty details: [INSERT PARTS AND LABOR WARRANTY]. H2: Parts We Replace Most Often For dishwasher repairs, the parts we replace most often include drain pumps, door latches, gaskets, spray arms, inlet valves, heating elements and control boards. We use quality OEM or equivalent parts, and we explain which options are available when more than one exists. H2: Brands We Service We repair dishwasher models from Bosch, Whirlpool, KitchenAid, GE, Samsung, LG, Maytag, Frigidaire, Miele, Thermador, and Electrolux, along with many others. Not sure whether your model is covered? Tell us the brand and model number from the label and we will confirm before booking. H2: Should You Repair or Replace Your Dishwasher? Dishwashers last about 9 to 12 years. Pump, valve, latch and filter repairs are cost-effective, while a failed tub or major leak on an older unit may call for replacement. Factors that help you decide include the age of the unit, the cost of the repair compared with a new appliance, how often it has broken down and how efficient it is compared with newer models. We give you an honest recommendation, even when that means telling you not to repair it. H2: What Affects the Cost of Dishwasher Repair The final price depends on the diagnosis, the part needed, the brand and how hard the appliance is to access. Rather than quoting a vague range over the phone, we diagnose first, give you a firm written price and wait for your approval. Diagnostic fee: [INSERT DIAGNOSTIC FEE, CREDITED TOWARD REPAIR IF APPLICABLE]. H2: Maintenance Tips to Prevent Future Breakdowns - Scrape plates rather than pre-rinsing, but don't leave large debris. - Clean the filter monthly. - Run hot water at the sink before starting a cycle. - Use rinse aid to improve drying and prevent spotting. Safety note: Turn off the water supply under the sink and cut power at the breaker if you see leaking. H2: Why Suffolk County Customers Choose [BUSINESS NAME] We are a local team that knows Long Island homes, from older North Shore houses to South Shore condos and apartments. Our technicians are [INSERT LICENSING / INSURANCE DETAILS], and we aim to show up on time, keep your home clean and explain every step in plain English. Customers value honest quotes, tidy work and repairs that last. H2: Dishwasher Repair Near You We provide service in these areas, each with its own local page: - Dishwasher Repair in Huntington, NY - Dishwasher Repair in Smithtown, NY - Dishwasher Repair in Islip, NY - Dishwasher Repair in Babylon, NY - Dishwasher Repair in Patchogue, NY If your neighborhood is not listed, contact us. We may still be able to help, depending on your location. H2: Frequently Asked Questions Q: Why is there standing water in my dishwasher? A: Most often a clogged filter or drain hose, a blocked garbage disposal connection or a failed drain pump. Q: Why are my dishes still dirty after a full cycle? A: Blocked spray arms or a dirty filter usually restrict cleaning. Low water pressure or a failing pump can also be the cause. Q: Do you repair integrated and drawer dishwashers? A: Yes. We service built-in, panel-ready, drawer and portable dishwashers. Q: How much does dishwasher repair cost in Suffolk County? A: The cost depends on the fault, the part and the brand. We diagnose the problem first and give a written quote so you know the price before work begins. Q: How quickly can you schedule dishwasher repair? A: Availability varies by day and location. [INSERT YOUR SAME-DAY / NEXT-DAY POLICY HERE]. Call us and we will offer the earliest appointment window. Q: Do you guarantee your repairs? A: Yes. We back our work with a [INSERT WARRANTY LENGTH] parts and labor warranty, so you are covered if the same problem returns. H2: Schedule Your Dishwasher Repair Today Don't live with a broken dishwasher. Call [PHONE] or use our online booking form to schedule a technician anywhere in Suffolk County. | P11: All Services -> /appliance-repair-services/ Garbage Disposal Repair -> /garbage-disposal-repair/ Washing Machine Repair -> /washer-repair/ Oven Repair -> /oven-repair/ Dishwasher Repair in Huntington, NY -> /dishwasher-repair/huntington-ny/ Dishwasher Repair in Smithtown, NY -> /dishwasher-repair/smithtown-ny/ Dishwasher Repair in Islip, NY -> /dishwasher-repair/islip-ny/ Dishwasher Repair in Babylon, NY -> /dishwasher-repair/babylon-ny/ Dishwasher Repair in Patchogue, NY -> /dishwasher-repair/patchogue-ny/ Brands We Service -> /appliance-brands/ Service Areas -> /service-areas/ Contact Us -> /contact/ Reviews -> /reviews/ | Q11: =LEN(P11)-LEN(SUBSTITUTE(P11,CHAR(10),""))+1 -> 13 | R11: EPA WaterSense water-efficiency program -> https://www.epa.gov/watersense ENERGY STAR certified products -> https://www.energystar.gov/products | S11: Service | T11: To do
A12: 11 | B12: Core Service | C12: Oven Repair | D12: Oven Repair | E12: /oven-repair/ | F12: Oven Repair Suffolk County NY | G12: Oven Repair Suffolk County, NY | [BUSINESS NAME] | H12: =LEN(G12) -> 48 | I12: Need oven repair in Suffolk County, NY? Local technicians fix heating, temperature and door problems with upfront quotes. Call [PHONE] to book. | J12: =LEN(I12) -> 143 | K12: 800 | L12: 1200 | M12: 945 | N12: =IF(AND(M12>=K12,M12<=L12),"OK","Check") -> OK | O12: H1: Oven Repair in Suffolk County, NY When your oven won't heat or bakes unevenly, dinner plans fall apart. We repair single and double wall ovens, electric and gas ovens and convection models. [BUSINESS NAME] serves homeowners and businesses across Suffolk County, including Huntington, Smithtown, Islip, Babylon and Patchogue, with clear upfront pricing and no work started until you approve the quote. If you are searching for oven repair near you, our technicians diagnose the real cause instead of guessing, which saves you from paying for parts you don't need. Call [PHONE] or request a visit online to get started. H2: Signs Your Oven Needs Repair Appliances rarely fail without warning. These are the most common oven problems we see across Suffolk County and what usually causes them: H3: Oven not heating A failed bake or broil element, igniter, thermal fuse or control board. H3: Uneven baking or wrong temperature A faulty temperature sensor, thermostat or worn door gasket causing heat loss. H3: Oven won't turn on A control board, relay or wiring fault, or a tripped breaker. H3: Door won't close or latch A worn hinge, spring or latch assembly. H3: Self-clean cycle failing A faulty door lock motor, thermal fuse or control issue. H3: Gas smell or slow ignition A weak igniter or gas valve problem, which should be treated as a safety issue. H2: Our Oven Repair Process We test heating components and sensors, verify temperature accuracy and inspect the door, controls and gas supply where applicable. You get a written estimate before we begin. 1. Book your visit by phone or online and tell us the brand, model and symptoms. 2. A technician arrives within the appointment window and inspects the oven. 3. You receive a clear explanation of the fault and a firm price before any work begins. 4. We complete the repair, test the appliance and show you the result. 5. You receive a written invoice and our warranty details: [INSERT PARTS AND LABOR WARRANTY]. H2: Parts We Replace Most Often For oven repairs, the parts we replace most often include bake and broil elements, igniters, temperature sensors, door gaskets, hinges and control boards. We use quality OEM or equivalent parts, and we explain which options are available when more than one exists. H2: Brands We Service We repair oven models from GE, Whirlpool, Frigidaire, Samsung, LG, KitchenAid, Bosch, Thermador, Wolf, Viking, Jenn-Air, and Miele, along with many others. Not sure whether your model is covered? Tell us the brand and model number from the label and we will confirm before booking. H2: Should You Repair or Replace Your Oven? Ovens commonly last 13 to 15 years. Elements, igniters, sensors and gaskets are inexpensive repairs, while a failed control on an older unit can approach replacement cost. Factors that help you decide include the age of the unit, the cost of the repair compared with a new appliance, how often it has broken down and how efficient it is compared with newer models. We give you an honest recommendation, even when that means telling you not to repair it. H2: What Affects the Cost of Oven Repair The final price depends on the diagnosis, the part needed, the brand and how hard the appliance is to access. Rather than quoting a vague range over the phone, we diagnose first, give you a firm written price and wait for your approval. Diagnostic fee: [INSERT DIAGNOSTIC FEE, CREDITED TOWARD REPAIR IF APPLICABLE]. H2: Maintenance Tips to Prevent Future Breakdowns - Do not line the oven floor with foil, which can damage elements. - Wipe spills promptly to protect sensors and elements. - Check the door seal regularly for tears. - Use the self-clean cycle sparingly. Safety note: If you smell gas, leave the home, avoid switches and call your gas utility and emergency services first. H2: Why Suffolk County Customers Choose [BUSINESS NAME] We are a local team that knows Long Island homes, from older North Shore houses to South Shore condos and apartments. Our technicians are [INSERT LICENSING / INSURANCE DETAILS], and we aim to show up on time, keep your home clean and explain every step in plain English. Customers value honest quotes, tidy work and repairs that last. H2: Oven Repair Near You We provide service in these areas, each with its own local page: - Oven Repair in Huntington, NY - Oven Repair in Smithtown, NY - Oven Repair in Islip, NY - Oven Repair in Babylon, NY - Oven Repair in Patchogue, NY If your neighborhood is not listed, contact us. We may still be able to help, depending on your location. H2: Frequently Asked Questions Q: Why isn't my electric oven heating? A: A burned-out bake element or failed thermal fuse is common. A technician can test each part quickly. Q: Why is my oven temperature inaccurate? A: A faulty sensor or a worn control often causes this, and calibration can sometimes correct it. Q: Do you repair gas ovens? A: Yes. We repair gas ovens, igniters and valves with strict attention to safety. Q: How much does oven repair cost in Suffolk County? A: The cost depends on the fault, the part and the brand. We diagnose the problem first and give a written quote so you know the price before work begins. Q: How quickly can you schedule oven repair? A: Availability varies by day and location. [INSERT YOUR SAME-DAY / NEXT-DAY POLICY HERE]. Call us and we will offer the earliest appointment window. Q: Do you guarantee your repairs? A: Yes. We back our work with a [INSERT WARRANTY LENGTH] parts and labor warranty, so you are covered if the same problem returns. H2: Schedule Your Oven Repair Today Don't live with a broken oven. Call [PHONE] or use our online booking form to schedule a technician anywhere in Suffolk County. | P12: All Services -> /appliance-repair-services/ Stove & Range Repair -> /stove-range-repair/ Cooktop Repair -> /cooktop-repair/ Microwave Repair -> /microwave-repair/ Oven Repair in Huntington, NY -> /oven-repair/huntington-ny/ Oven Repair in Smithtown, NY -> /oven-repair/smithtown-ny/ Oven Repair in Islip, NY -> /oven-repair/islip-ny/ Oven Repair in Babylon, NY -> /oven-repair/babylon-ny/ Oven Repair in Patchogue, NY -> /oven-repair/patchogue-ny/ Brands We Service -> /appliance-brands/ Service Areas -> /service-areas/ Contact Us -> /contact/ Reviews -> /reviews/ | Q12: =LEN(P12)-LEN(SUBSTITUTE(P12,CHAR(10),""))+1 -> 13 | R12: NFPA cooking safety guidance -> https://www.nfpa.org/education-and-research/home-fire-safety/cooking ENERGY STAR certified products -> https://www.energystar.gov/products | S12: Service | T12: To do
A13: 12 | B13: Core Service | C13: Stove & Range Repair | D13: Stove & Range Repair | E13: /stove-range-repair/ | F13: Stove & Range Repair Suffolk County NY | G13: Stove & Range Repair Suffolk County, NY | [BUSINESS NAME] | H13: =LEN(G13) -> 57 | I13: Need stove & range repair in Suffolk County, NY? Local technicians fix burner, igniter and oven problems with upfront quotes. Call [PHONE] to book. | J13: =LEN(I13) -> 147 | K13: 800 | L13: 1200 | M13: 956 | N13: =IF(AND(M13>=K13,M13<=L13),"OK","Check") -> OK | O13: H1: Stove & Range Repair in Suffolk County, NY Your range is the workhorse of the kitchen, and a single failed burner or oven element can disrupt daily meals. We repair gas, electric, dual-fuel and induction stoves and ranges. [BUSINESS NAME] serves homeowners and businesses across Suffolk County, including Huntington, Smithtown, Islip, Babylon and Patchogue, with clear upfront pricing and no work started until you approve the quote. If you are searching for stove & range repair near you, our technicians diagnose the real cause instead of guessing, which saves you from paying for parts you don't need. Call [PHONE] or request a visit online to get started. H2: Signs Your Stove & Range Needs Repair Appliances rarely fail without warning. These are the most common stove & range problems we see across Suffolk County and what usually causes them: H3: Burner won't light or clicks constantly A dirty or wet burner, a failed igniter or a faulty spark module. H3: Electric burner not heating A worn burner element, loose receptacle or failed infinite switch. H3: Uneven flame or yellow flame Clogged burner ports or an incorrect air/gas mixture. H3: Oven side not working A failed bake element, igniter or control board. H3: Knobs or controls unresponsive A bad switch, control board or electronic touchpad. H3: Sparking or burning smell Damaged wiring or a failing element, which needs prompt attention. H2: Our Stove & Range Repair Process We inspect the burners, igniters, switches and oven components together, test gas and electrical supply and explain which repairs are essential and which can wait. 1. Book your visit by phone or online and tell us the brand, model and symptoms. 2. A technician arrives within the appointment window and inspects the stove & range. 3. You receive a clear explanation of the fault and a firm price before any work begins. 4. We complete the repair, test the appliance and show you the result. 5. You receive a written invoice and our warranty details: [INSERT PARTS AND LABOR WARRANTY]. H2: Parts We Replace Most Often For stove & range repairs, the parts we replace most often include surface elements, igniters, spark modules, infinite switches, burner caps and control boards. We use quality OEM or equivalent parts, and we explain which options are available when more than one exists. H2: Brands We Service We repair stove & range models from GE, Whirlpool, Frigidaire, Samsung, LG, KitchenAid, Bosch, Viking, Wolf, Thermador, Maytag, and Jenn-Air, along with many others. Not sure whether your model is covered? Tell us the brand and model number from the label and we will confirm before booking. H2: Should You Repair or Replace Your Stove & Range? Ranges generally last 13 to 15 years. Most burner, switch and igniter repairs are inexpensive, but a failed main control on an old range may justify replacement. Factors that help you decide include the age of the unit, the cost of the repair compared with a new appliance, how often it has broken down and how efficient it is compared with newer models. We give you an honest recommendation, even when that means telling you not to repair it. H2: What Affects the Cost of Stove & Range Repair The final price depends on the diagnosis, the part needed, the brand and how hard the appliance is to access. Rather than quoting a vague range over the phone, we diagnose first, give you a firm written price and wait for your approval. Diagnostic fee: [INSERT DIAGNOSTIC FEE, CREDITED TOWARD REPAIR IF APPLICABLE]. H2: Maintenance Tips to Prevent Future Breakdowns - Keep burner ports clean with a soft brush. - Make sure burner caps are seated correctly. - Clean spills on electric elements only when cool. - Replace damaged drip pans and receptacles early. Safety note: If you smell gas, leave the house and call your gas utility or emergency services before anything else. H2: Why Suffolk County Customers Choose [BUSINESS NAME] We are a local team that knows Long Island homes, from older North Shore houses to South Shore condos and apartments. Our technicians are [INSERT LICENSING / INSURANCE DETAILS], and we aim to show up on time, keep your home clean and explain every step in plain English. Customers value honest quotes, tidy work and repairs that last. H2: Stove & Range Repair Near You We provide service in these areas, each with its own local page: - Stove & Range Repair in Huntington, NY - Stove & Range Repair in Smithtown, NY - Stove & Range Repair in Islip, NY - Stove & Range Repair in Babylon, NY - Stove & Range Repair in Patchogue, NY If your neighborhood is not listed, contact us. We may still be able to help, depending on your location. H2: Frequently Asked Questions Q: Why does my gas burner click but not light? A: Moisture, food debris or a worn igniter or spark module is typically the cause. Q: Why is only one electric burner not working? A: The element or its receptacle has usually failed, which is a straightforward repair. Q: Do you repair slide-in, freestanding and dual-fuel ranges? A: Yes, we service all common range types and major brands. Q: How much does stove & range repair cost in Suffolk County? A: The cost depends on the fault, the part and the brand. We diagnose the problem first and give a written quote so you know the price before work begins. Q: How quickly can you schedule stove & range repair? A: Availability varies by day and location. [INSERT YOUR SAME-DAY / NEXT-DAY POLICY HERE]. Call us and we will offer the earliest appointment window. Q: Do you guarantee your repairs? A: Yes. We back our work with a [INSERT WARRANTY LENGTH] parts and labor warranty, so you are covered if the same problem returns. H2: Schedule Your Stove & Range Repair Today Don't live with a broken stove & range. Call [PHONE] or use our online booking form to schedule a technician anywhere in Suffolk County. | P13: All Services -> /appliance-repair-services/ Oven Repair -> /oven-repair/ Cooktop Repair -> /cooktop-repair/ Microwave Repair -> /microwave-repair/ Stove & Range Repair in Huntington, NY -> /stove-range-repair/huntington-ny/ Stove & Range Repair in Smithtown, NY -> /stove-range-repair/smithtown-ny/ Stove & Range Repair in Islip, NY -> /stove-range-repair/islip-ny/ Stove & Range Repair in Babylon, NY -> /stove-range-repair/babylon-ny/ Stove & Range Repair in Patchogue, NY -> /stove-range-repair/patchogue-ny/ Brands We Service -> /appliance-brands/ Service Areas -> /service-areas/ Contact Us -> /contact/ Reviews -> /reviews/ | Q13: =LEN(P13)-LEN(SUBSTITUTE(P13,CHAR(10),""))+1 -> 13 | R13: NFPA cooking safety guidance -> https://www.nfpa.org/education-and-research/home-fire-safety/cooking ENERGY STAR certified products -> https://www.energystar.gov/products | S13: Service | T13: To do
... A99: 98 | B99: Service + Location | C99: Luxury Appliance Repair | D99: Luxury Appliance Repair Patchogue | E99: /luxury-appliance-repair/patchogue-ny/ | F99: Luxury Appliance Repair Patchogue NY | G99: Luxury Appliance Repair Patchogue, NY | Local Technicians | H99: =LEN(G99) -> 57 | I99: Looking for luxury appliance repair in Patchogue, NY? Local technicians fix high-end refrigeration and cooking faults. Upfront quotes. Call [PHONE]. | J99: =LEN(I99) -> 148 | K99: 700 | L99: 1000 | M99: 781 | N99: =IF(AND(M99>=K99,M99<=L99),"OK","Check") -> OK | O99: H1: Luxury Appliance Repair in Patchogue, NY Patchogue is a lively waterfront village with a walkable downtown, surrounded by neighborhoods of single-family homes, condos and apartments. When your luxury appliance fails, you need a technician who understands local homes and gets the job done right the first time. [BUSINESS NAME] provides luxury appliance repair in Patchogue and nearby neighborhoods, covering high-end refrigeration and cooking faults for homeowners, renters and property managers. Waterfront condos and renovated homes around Patchogue and Bellport often include upgraded, built-in kitchen appliances. That is why Patchogue residents often call us for luxury appliance problems before they turn into costly breakdowns. Call [PHONE] or book online and we will arrange an appointment at your Patchogue address. H2: Luxury Appliance Repair Throughout Patchogue Our technicians travel to homes and businesses across Patchogue, including Patchogue Village, East Patchogue, North Patchogue, Blue Point, Bellport, Medford, and Holbrook. Wherever you are located, we bring tools and common parts for most luxury appliance repairs to the first visit. H2: Common Luxury Appliance Problems We Fix in Patchogue H3: Integrated refrigerator not cooling Sealed-system, fan or control issues unique to built-in units. H3: Professional range igniter failure Worn igniters and spark modules. H3: Control or display errors Electronic boards or sensors requiring brand-specific diagnostics. H3: Inconsistent oven temperature A faulty sensor or convection fan. H3: Water dispenser or ice faults Valve, filter or module problems. H3: Panel alignment or door issues Hinges, gaskets and cabinetry fit. H2: How Patchogue Homeowners Can Get the Most From Their Luxury Appliance - Follow the manufacturer's maintenance schedule. - Use only recommended cleaners on stainless and glass. - Keep ventilation openings clear. - Service early to protect warranty coverage. H2: Our Repair Process in Patchogue We use manufacturer-specified parts and procedures wherever available, protect your cabinetry and finishes and explain every step before work begins. 1. Call or book online and describe the problem with your luxury appliance. 2. We confirm your Patchogue address and schedule an appointment window. 3. The technician diagnoses the fault and gives a firm quote. 4. With your approval, we repair and test the appliance. 5. You receive an invoice and warranty details: [INSERT WARRANTY]. H2: Brands We Service in Patchogue We repair luxury appliance models from Sub-Zero, Wolf, Viking, Thermador, Miele, Gaggenau, Bosch Benchmark, Jenn-Air, Dacor, Fisher & Paykel, Cove, and Liebherr and more for customers in Patchogue. If you are unsure about your model, send us the model number and we will confirm we can help. H2: Repair or Replace? Advice for Patchogue Residents Because luxury appliances are costly, repair is frequently the best value, particularly for sealed-system, igniter and board faults. H2: Why Patchogue Customers Choose [BUSINESS NAME] As a Suffolk County company, we know the area and the homes in it. We provide upfront quotes, treat your home with care and explain the problem clearly. Licensing and insurance: [INSERT DETAILS]. Customers in Patchogue call us because we respect their time and their budget. H2: Luxury Appliance Repair FAQs for Patchogue Q: Do you provide luxury appliance repair in Patchogue? A: Yes. We serve Patchogue and nearby areas including Patchogue Village, East Patchogue, North Patchogue, and Blue Point. Contact us to confirm availability for your address. Q: How soon can you come to Patchogue for luxury appliance repair? A: Availability varies by day. [INSERT YOUR SAME-DAY / NEXT-DAY POLICY]. We will offer the earliest window we have. Q: How much does luxury appliance repair cost in Patchogue? A: We diagnose the issue first and give a written price before starting, so there are no surprises. [INSERT DIAGNOSTIC FEE POLICY]. Q: Do you repair Sub-Zero and Wolf appliances? A: Yes, we service premium brands including Sub-Zero, Wolf, Viking, Thermador and Miele. Q: Will repairs affect my warranty? A: Check your warranty terms, and contact us if you are unsure which repairs are covered. H2: Book Luxury Appliance Repair in Patchogue Today Call [PHONE] or request service online. Our team will get your luxury appliance working again. H2: Preparing for Your Patchogue Service Visit A few simple steps help the technician work faster. Clear the area around your luxury appliance so there is room to work, note when the problem started and any error codes, and keep the model number handy. If the appliance is leaking, switch off its power and water supply where it is safe to do so. For apartment and condo buildings in Patchogue, let us know about parking, access or building rules in advance so your appointment runs smoothly. H2: Other Appliance Repair Services in Patchogue Often one appliance failing is a sign that others in the home are due for a check. In Patchogue we also repair wine cooler, cooktop, and refrigerator, along with every other appliance listed on our services page. Combining repairs in one visit can save you time. | P99: Luxury Appliance Repair Suffolk County -> /luxury-appliance-repair/ Appliance Repair Patchogue -> /appliance-repair-patchogue-ny/ Luxury Appliance Repair in Islip, NY -> /luxury-appliance-repair/islip-ny/ Wine Cooler Repair in Patchogue -> /wine-cooler-repair/patchogue-ny/ Cooktop Repair in Patchogue -> /cooktop-repair/patchogue-ny/ Contact Us -> /contact/ | Q99: =LEN(P99)-LEN(SUBSTITUTE(P99,CHAR(10),""))+1 -> 6 | R99: Town of Brookhaven -> https://www.brookhavenny.gov/ Sub-Zero Wolf Cove official site -> https://www.subzero-wolf.com/ | S99: Service (areaServed: Patchogue) | T99: To do

Sheet Link Map
A1: Source Page | B1: Anchor Text | C1: Target | D1: Link Type
A2: / | B2: Refrigerator Repair | C2: /refrigerator-repair/ | D2: Internal
A3: / | B3: Freezer Repair | C3: /freezer-repair/ | D3: Internal
A4: / | B4: Washing Machine Repair | C4: /washer-repair/ | D4: Internal
A5: / | B5: Dryer Repair | C5: /dryer-repair/ | D5: Internal
A6: / | B6: Dishwasher Repair | C6: /dishwasher-repair/ | D6: Internal
A7: / | B7: Oven Repair | C7: /oven-repair/ | D7: Internal
A8: / | B8: Stove & Range Repair | C8: /stove-range-repair/ | D8: Internal
A9: / | B9: Cooktop Repair | C9: /cooktop-repair/ | D9: Internal
A10: / | B10: Appliance Repair Huntington | C10: /appliance-repair-huntington-ny/ | D10: Internal
A11: / | B11: Appliance Repair Smithtown | C11: /appliance-repair-smithtown-ny/ | D11: Internal
A12: / | B12: Appliance Repair Islip | C12: /appliance-repair-islip-ny/ | D12: Internal
... A987: /luxury-appliance-repair/patchogue-ny/ | B987: Sub-Zero Wolf Cove official site | C987: https://www.subzero-wolf.com/ | D987: External

Sheet Blog Topics
A1: # | B1: Article Title | C1: Link To (service page) | D1: Target Keyword | E1: Also Link To (town pages)
A2: 1 | B2: Why Your Refrigerator Is Not Cooling: 7 Common Causes | C2: /refrigerator-repair/ | D2: refrigerator not cooling | E2: /refrigerator-repair/huntington-ny/, /refrigerator-repair/smithtown-ny/
A3: 2 | B3: Why Is My Freezer Frosting Up? Causes and Fixes | C3: /freezer-repair/ | D3: freezer frost buildup | E3: /freezer-repair/huntington-ny/, /freezer-repair/smithtown-ny/
A4: 3 | B4: Washing Machine Not Draining? Check These Things First | C4: /washer-repair/ | D4: washer not draining | E4: /washer-repair/huntington-ny/, /washer-repair/smithtown-ny/
A5: 4 | B5: Why a Dryer Takes Too Long to Dry (and When It Is a Fire Risk) | C5: /dryer-repair/ | D5: dryer takes too long to dry | E5: /dryer-repair/huntington-ny/, /dryer-repair/smithtown-ny/
A6: 5 | B6: Dishwasher Not Cleaning Dishes? Common Causes | C6: /dishwasher-repair/ | D6: dishwasher not cleaning | E6: /dishwasher-repair/huntington-ny/, /dishwasher-repair/smithtown-ny/
A7: 6 | B7: Oven Not Heating Evenly: What Technicians Check | C7: /oven-repair/ | D7: oven not heating evenly | E7: /oven-repair/huntington-ny/, /oven-repair/smithtown-ny/
A8: 7 | B8: Gas Stove Burner Clicking or Won't Light: Causes | C8: /stove-range-repair/ | D8: gas stove won't light | E8: /stove-range-repair/huntington-ny/, /stove-range-repair/smithtown-ny/
A9: 8 | B9: Induction vs Radiant vs Gas Cooktops: Repair Considerations | C9: /cooktop-repair/ | D9: cooktop repair | E9: /cooktop-repair/huntington-ny/, /cooktop-repair/smithtown-ny/
A10: 9 | B10: Microwave Sparking: Is It Safe to Keep Using? | C10: /microwave-repair/ | D10: microwave sparking | E10: /microwave-repair/huntington-ny/, /microwave-repair/smithtown-ny/
A11: 10 | B11: Refrigerator Ice Maker Not Working: Troubleshooting Guide | C11: /ice-maker-repair/ | D11: ice maker not working | E11: /ice-maker-repair/huntington-ny/, /ice-maker-repair/smithtown-ny/
A12: 11 | B12: How to Protect a Wine Collection When Your Wine Cooler Fails | C12: /wine-cooler-repair/ | D12: wine cooler not cooling | E12: /wine-cooler-repair/huntington-ny/, /wine-cooler-repair/smithtown-ny/
A13: 12 | B13: Garbage Disposal Humming but Not Spinning: What to Do | C13: /garbage-disposal-repair/ | D13: garbage disposal humming | E13: /garbage-disposal-repair/huntington-ny/, /garbage-disposal-repair/smithtown-ny/
... A15: 14 | B15: Is It Worth Repairing a High-End Appliance? | C15: /luxury-appliance-repair/ | D15: repair or replace luxury appliance | E15: /luxury-appliance-repair/huntington-ny/, /luxury-appliance-repair/smithtown-ny/
